auto_comsight/__init__.py
auto_comsight/main.py
auto_comsight/prompts.py
auto_comsight-2025.12.22091049.dist-info/METADATA
auto_comsight-2025.12.22091049.dist-info/WHEEL
auto_comsight-2025.12.22091049.dist-info/top_level.txt
auto_comsight-2025.12.22091049.dist-info/RECORD
