Metadata-Version: 2.4
Name: auto-comsight
Version: 2025.12.22091049
Summary: Auto-comsight extracts structured insights from text about autonomous systems, categorizing components, challenges, and optimizations.
Author-email: auto-comsight <hi@eugene.plus>
License: MIT
Project-URL: Homepage, https://github.com/chigwell/auto-comsight
Requires-Python: >=3.9
Requires-Dist: langchain-llm7>=0.0.0
Requires-Dist: llmatch-messages>=0.0.0
Requires-Dist: langchain-core>=0.3.0
